[
  { "id": 1051, "title": "숫자 정사각형" },
  { "id": 1063, "title": "킹" },
  { "id": 1138, "title": "한 줄로 서기" },
  { "id": 1213, "title": "팰린드롬 만들기" },
  { "id": 1270, "title": "전쟁 - 땅따먹기" },
  { "id": 1283, "title": "단축키 지정" },
  { "id": 1347, "title": "미로 만들기" },
  { "id": 1411, "title": "비슷한 단어" },
  { "id": 1515, "title": "수 이어 쓰기" },
  { "id": 1614, "title": "영식이의 손가락" },
  { "id": 1706, "title": "크로스워드" },
  { "id": 1713, "title": "후보 추천하기" },
  { "id": 1783, "title": "병든 나이트" },
  { "id": 1913, "title": "달팽이" },
  { "id": 1966, "title": "프린터 큐" },
  { "id": 1972, "title": "놀라운 문자열" },
  { "id": 1986, "title": "체스" },
  { "id": 2002, "title": "추월" },
  { "id": 2108, "title": "통계학" },
  { "id": 2290, "title": "LCD Test" },
  { "id": 2304, "title": "창고 다각형" },
  { "id": 2477, "title": "참외밭" },
  { "id": 2503, "title": "숫자 야구" },
  { "id": 2564, "title": "경비원" },
  { "id": 2607, "title": "비슷한 단어" },
  { "id": 2615, "title": "오목" },
  { "id": 2621, "title": "카드게임" },
  { "id": 2659, "title": "십자카드 문제" },
  { "id": 2824, "title": "최대공약수" },
  { "id": 2852, "title": "NBA 농구" },
  { "id": 3085, "title": "사탕 게임" },
  { "id": 3107, "title": "IPv6" },
  { "id": 3613, "title": "Java vs C++" },
  { "id": 3758, "title": "KCPC" },
  { "id": 5212, "title": "지구 온난화" },
  { "id": 5464, "title": "주차장" },
  { "id": 6986, "title": "절사평균" },
  { "id": 8911, "title": "거북이" },
  { "id": 9017, "title": "크로스 컨트리" },
  { "id": 9081, "title": "단어 맞추기" },
  { "id": 10157, "title": "자리배정" },
  { "id": 10655, "title": "마라톤 1" },
  { "id": 10973, "title": "이전 순열" },
  { "id": 10997, "title": "별 찍기 - 22" },
  { "id": 12873, "title": "기념품" },
  { "id": 12933, "title": "오리" },
  { "id": 13335, "title": "트럭" },
  { "id": 13414, "title": "수강신청" },
  { "id": 14713, "title": "앵무새" },
  { "id": 15787, "title": "기차가 어둠을 헤치고 은하수를" },
  { "id": 16918, "title": "봄버맨" },
  { "id": 16922, "title": "로마 숫자 만들기" },
  { "id": 16924, "title": "십자가 찾기" },
  { "id": 16931, "title": "겉넓이 구하기" },
  { "id": 16937, "title": "두 스티커" },
  { "id": 16967, "title": "배열 복원하기" },
  { "id": 17204, "title": "죽음의 게임" },
  { "id": 17276, "title": "배열 돌리기" },
  { "id": 17413, "title": "단어 뒤집기 2" },
  { "id": 17829, "title": "222-풀링" },
  { "id": 17952, "title": "과제는 끝나지 않아!" },
  { "id": 18111, "title": "마인크래프트" },
  { "id": 18917, "title": "수열과 쿼리 38" },
  { "id": 19583, "title": "싸이버개강총회" },
  { "id": 19638, "title": "센티와 마법의 뿅망치" },
  { "id": 20006, "title": "랭킹전 대기열" },
  { "id": 20301, "title": "반전 요세푸스" },
  { "id": 21314, "title": "민겸 수" },
  { "id": 24060, "title": "알고리즘 수업 - 병합 정렬 1" },
  { "id": 26215, "title": "눈 치우기" },
  { "id": 30804, "title": "과일 탕후루" }
]
